knxrcore/__init__.py
knxrcore/argparser/__init__.py
knxrcore/argparser/argparse.py
knxrcore/error/__init__.py
knxrcore/error/argparseException.py
knxrcore/error/baseError.py
knxrcore/logger/__init__.py
knxrcore/logger/logger.py
knxrcore/sql/__init__.py
knxrcore/sql/mysql.py
knxrcore/utils/__init__.py
knxrcore/utils/argparseUtils.py
knxrcore/utils/loggerUtils.py
knxrcore/utils/utils.py
knxrcore/wrapper/__init__.py
knxrcore/wrapper/connection.py
kenexar_core-2.5.0.dist-info/LICENSE
kenexar_core-2.5.0.dist-info/METADATA
kenexar_core-2.5.0.dist-info/WHEEL
kenexar_core-2.5.0.dist-info/top_level.txt
kenexar_core-2.5.0.dist-info/RECORD
