Metadata-Version: 2.1
Name: kenexar-core
Version: 2.5.0
Summary: This is the base package for the most Kenexar py projects.
Home-page: https://github.com/kenexar/kenexar-core
Author: exersalza
License: MIT
Project-URL: Docs, https://kenexar.github.io/kenexar-core/
Project-URL: Source, https://github.com/kenexar/kenexar-core
Project-URL: Issues, https://github.com/kenexar/kenexar-core/issues
Classifier: Intended Audience :: Developers
Classifier: License :: OSI Approved :: MIT License
Classifier: Operating System :: OS Independent
Classifier: Programming Language :: Python :: 3
Classifier: Topic :: Software Development
License-File: LICENSE
Requires-Dist: mysql-connector-python
Requires-Dist: pytz
Requires-Dist: requests
